g42cloudsdkmpc/__init__.py
g42cloudsdkmpc/v1/__init__.py
g42cloudsdkmpc/v1/mpc_async_client.py
g42cloudsdkmpc/v1/mpc_client.py
g42cloudsdkmpc/v1/model/__init__.py
g42cloudsdkmpc/v1/model/agencies_task_req.py
g42cloudsdkmpc/v1/model/animated_graphics_output_param.py
g42cloudsdkmpc/v1/model/animated_graphics_task.py
g42cloudsdkmpc/v1/model/audio.py
g42cloudsdkmpc/v1/model/audio_file.py
g42cloudsdkmpc/v1/model/audio_info.py
g42cloudsdkmpc/v1/model/audio_process.py
g42cloudsdkmpc/v1/model/audio_track.py
g42cloudsdkmpc/v1/model/av_parameters.py
g42cloudsdkmpc/v1/model/basic_task_info.py
g42cloudsdkmpc/v1/model/basic_watermark.py
g42cloudsdkmpc/v1/model/bucket_authorized_req.py
g42cloudsdkmpc/v1/model/cancel_remux_task_request.py
g42cloudsdkmpc/v1/model/cancel_remux_task_response.py
g42cloudsdkmpc/v1/model/clip_info.py
g42cloudsdkmpc/v1/model/common.py
g42cloudsdkmpc/v1/model/common_create_task_req.py
g42cloudsdkmpc/v1/model/common_create_task_rsp.py
g42cloudsdkmpc/v1/model/common_query_task_rsp.py
g42cloudsdkmpc/v1/model/common_task.py
g42cloudsdkmpc/v1/model/common_task_meta.py
g42cloudsdkmpc/v1/model/concat_info.py
g42cloudsdkmpc/v1/model/create_agencies_task_request.py
g42cloudsdkmpc/v1/model/create_agencies_task_response.py
g42cloudsdkmpc/v1/model/create_animated_graphics_task_req.py
g42cloudsdkmpc/v1/model/create_animated_graphics_task_request.py
g42cloudsdkmpc/v1/model/create_animated_graphics_task_response.py
g42cloudsdkmpc/v1/model/create_editing_job_req.py
g42cloudsdkmpc/v1/model/create_editing_job_request.py
g42cloudsdkmpc/v1/model/create_editing_job_response.py
g42cloudsdkmpc/v1/model/create_encrypt_req.py
g42cloudsdkmpc/v1/model/create_encrypt_task_request.py
g42cloudsdkmpc/v1/model/create_encrypt_task_response.py
g42cloudsdkmpc/v1/model/create_extract_task_req.py
g42cloudsdkmpc/v1/model/create_extract_task_request.py
g42cloudsdkmpc/v1/model/create_extract_task_response.py
g42cloudsdkmpc/v1/model/create_mb_tasks_report_request.py
g42cloudsdkmpc-0.0.10b0.dist-info/LICENSE
g42cloudsdkmpc-0.0.10b0.dist-info/METADATA
g42cloudsdkmpc-0.0.10b0.dist-info/WHEEL
g42cloudsdkmpc-0.0.10b0.dist-info/top_level.txt
g42cloudsdkmpc-0.0.10b0.dist-info/RECORD
